{
  "asset_version": "2026032820",
  "bbox": [
    -109.0,
    24.0,
    -87.0,
    39.0
  ],
  "clipped_grib_path": "data\\processed\\products\\2026032820\\m00\\gust_surface\\f008\\south_central.grib2",
  "display_path": "2026032820/m00/gust_surface/f008/south_central",
  "domain_id": "south_central",
  "field_key": "GUST:surface",
  "forecast_hour": 8,
  "long_name": "Wind Speed (Gust)",
  "member": "m00",
  "mobile_preview_url": "./static-api/products/2026032820/m00/gust_surface/f008/south_central.mobile.webp",
  "native": false,
  "netcdf_path": "data\\processed\\products\\2026032820\\m00\\gust_surface\\f008\\south_central.nc",
  "overlay_id": "gust_surface",
  "preview_url": "./static-api/products/2026032820/m00/gust_surface/f008/south_central.preview.png",
  "run_id": "2026032820",
  "shape": [
    1,
    569,
    766
  ],
  "static_export": true,
  "stats": {
    "max": 26.1200008392334,
    "min": 1.159999966621399
  },
  "style": {
    "colors": [
      "#0b1840",
      "#3c6db5",
      "#70b796",
      "#facc40",
      "#db5231"
    ],
    "labels": [
      "0",
      "15",
      "30",
      "50",
      "75"
    ],
    "palette": "wind",
    "range": [
      0.0,
      40.0
    ],
    "rawUnits": "m/s",
    "transform": "mps_to_mph",
    "type": "continuous",
    "units": "mph"
  },
  "units": "m/s",
  "variable_name": "GUST_surface"
}